spatialtsp/__init__.py
spatialtsp/common.py
spatialtsp/spatialtsp.py
spatialtsp/utils.py
spatialtsp-0.0.5.dist-info/LICENSE
spatialtsp-0.0.5.dist-info/METADATA
spatialtsp-0.0.5.dist-info/WHEEL
spatialtsp-0.0.5.dist-info/entry_points.txt
spatialtsp-0.0.5.dist-info/top_level.txt
spatialtsp-0.0.5.dist-info/RECORD
